.coveragerc
.editorconfig
.gitignore
.travis.yml
LICENSE
README.md
pyproject.toml
requirements.txt
requirements_dev.txt
setup.cfg
setup.py
.github/workflows/python-publish.yml
democritus_grammars/__init__.py
democritus_grammars/grammars.py
democritus_grammars/grammars_temp_utils.py
democritus_grammars.egg-info/PKG-INFO
democritus_grammars.egg-info/SOURCES.txt
democritus_grammars.egg-info/dependency_links.txt
democritus_grammars.egg-info/requires.txt
democritus_grammars.egg-info/top_level.txt
democritus_grammars.egg-info/zip-safe
tests/__init__.py
tests/test_grammars.py